{
"type": "FeatureCollection",
                                                                                
"features": [
{ "type": "Feature", "properties": { "id": 1, "SiteNumber": "Site 1" }, "geometry": { "type": "Point", "coordinates": [ 37.185015002903526, 36.208673618913821 ] } },
{ "type": "Feature", "properties": { "id": 2, "SiteNumber": "Site 2" }, "geometry": { "type": "Point", "coordinates": [ 37.148069335615993, 36.193145729763991 ] } },
{ "type": "Feature", "properties": { "id": 3, "SiteNumber": "Site 3" }, "geometry": { "type": "Point", "coordinates": [ 37.143785779988455, 36.222595174703329 ] } },
{ "type": "Feature", "properties": { "id": 4, "SiteNumber": "Site 4" }, "geometry": { "type": "Point", "coordinates": [ 37.163061780312383, 36.205728674419888 ] } },
{ "type": "Feature", "properties": { "id": 5, "SiteNumber": "Site 5" }, "geometry": { "type": "Point", "coordinates": [ 37.170022558207137, 36.18966534081661 ] } }
]
}
